fasthtml_auth/__init__.py
fasthtml_auth/admin_routes.py
fasthtml_auth/database.py
fasthtml_auth/forms.py
fasthtml_auth/init.py
fasthtml_auth/manager.py
fasthtml_auth/middleware.py
fasthtml_auth/models.py
fasthtml_auth/repository.py
fasthtml_auth/routes.py
fasthtml_auth/utils.py
fasthtml_auth-0.2.0.dist-info/licenses/LICENSE
fasthtml_auth-0.2.0.dist-info/METADATA
fasthtml_auth-0.2.0.dist-info/WHEEL
fasthtml_auth-0.2.0.dist-info/top_level.txt
fasthtml_auth-0.2.0.dist-info/RECORD
