Metadata-Version: 2.4
Name: fasthtml-auth
Version: 0.2.0
Summary: Complete authentication system for FastHTML applications with beautiful UI, role-based access control, and session management
Author-email: John Richmond <confusedjohn46@gmail.com>
Maintainer-email: John Richmond <confusedjohn46@gmail.com>
License: MIT License
Project-URL: Homepage, https://github.com/fromLittleAcorns/fasthtml-auth
Project-URL: Documentation, https://github.com/fromLittleAcorns/fasthtml-auth#readme
Project-URL: Repository, https://github.com/fromLittleAcorns/fasthtml-toolkit
Project-URL: Issues, https://github.com/fromLittleAcorns/fasthtml-auth/issues
Project-URL: Changelog, https://github.com/fromLittleAcorns/fasthtml-auth/blob/main/CHANGELOG.md
Keywords: fasthtml,authentication,web,framework,auth,login,session,bcrypt,monsterui
Classifier: Development Status :: 4 - Beta
Classifier: Intended Audience :: Developers
Classifier: License :: OSI Approved :: MIT License
Classifier: Programming Language :: Python :: 3
Classifier: Programming Language :: Python :: 3.8
Classifier: Programming Language :: Python :: 3.9
Classifier: Programming Language :: Python :: 3.10
Classifier: Programming Language :: Python :: 3.11
Classifier: Programming Language :: Python :: 3.12
Classifier: Topic :: Internet :: WWW/HTTP :: Dynamic Content
Classifier: Topic :: Internet :: WWW/HTTP :: WSGI :: Application
Classifier: Topic :: Security
Classifier: Topic :: Software Development :: Libraries :: Python Modules
Classifier: Topic :: Software Development :: User Interfaces
Requires-Python: >=3.8
License-File: LICENSE
Requires-Dist: python-fasthtml>=0.12.0
Requires-Dist: monsterui>=1.0.20
Requires-Dist: fastlite>=0.2.0
Requires-Dist: bcrypt>=4.0.0
Provides-Extra: dev
Requires-Dist: pytest>=7.0.0; extra == "dev"
Requires-Dist: pytest-asyncio>=0.21.0; extra == "dev"
Requires-Dist: pytest-cov>=4.0.0; extra == "dev"
Requires-Dist: black>=23.0.0; extra == "dev"
Requires-Dist: flake8>=6.0.0; extra == "dev"
Requires-Dist: mypy>=1.0.0; extra == "dev"
Requires-Dist: pre-commit>=3.0.0; extra == "dev"
Provides-Extra: docs
Requires-Dist: mkdocs>=1.4.0; extra == "docs"
Requires-Dist: mkdocs-material>=8.5.0; extra == "docs"
Requires-Dist: mkdocs-autorefs>=0.4.0; extra == "docs"
Dynamic: license-file
